ASTROMER/__init__.py
ASTROMER/models.py
ASTROMER/preprocessing.py
ASTROMER/utils.py
ASTROMER/core/__init__.py
ASTROMER/core/astromer.py
ASTROMER/core/attention.py
ASTROMER/core/classifier.py
ASTROMER/core/data.py
ASTROMER/core/encoder.py
ASTROMER/core/losses.py
ASTROMER/core/masking.py
ASTROMER/core/metrics.py
ASTROMER/core/output.py
ASTROMER/core/plots.py
ASTROMER/core/positional.py
ASTROMER/core/scheduler.py
ASTROMER/core/tboard.py
ASTROMER/core/utils.py
astromer-0.1.8.dist-info/METADATA
astromer-0.1.8.dist-info/WHEEL
astromer-0.1.8.dist-info/licenses/LICENSE
astromer-0.1.8.dist-info/RECORD
