Metadata-Version: 2.4
Name: ASTROMER
Version: 0.1.8
Summary: Creates light curves embeddings using ASTROMER
Project-URL: Homepage, https://github.com/astromer-science/python-library
Author-email: Cristobal Donoso-Oliva <cridonoso@inf.udec.cl>
License: MIT License
License-File: LICENSE
Keywords: ASTROMER,astronomy,deep learning,embbedings,light curves,photometry,transformers
Classifier: License :: OSI Approved :: MIT License
Classifier: Programming Language :: Python
Classifier: Programming Language :: Python :: 3
Classifier: Programming Language :: Python :: 3.7
Classifier: Programming Language :: Python :: 3.8
Classifier: Programming Language :: Python :: 3.9
Classifier: Programming Language :: Python :: 3.10
Classifier: Programming Language :: Python :: 3.11
Classifier: Programming Language :: Python :: 3.12
Requires-Python: >=3.7
Requires-Dist: joblib
Requires-Dist: numpy
Requires-Dist: pandas
Requires-Dist: pytest
Requires-Dist: readthedocs-sphinx-search
Requires-Dist: scikit-learn
Requires-Dist: scipy
Requires-Dist: seaborn
Requires-Dist: sphinx
Requires-Dist: sphinx-autodoc-typehints
Requires-Dist: sphinx-rtd-theme
Requires-Dist: tensorflow>=2.6
Requires-Dist: tqdm
Provides-Extra: dev
Requires-Dist: bumpver; extra == 'dev'
Requires-Dist: pip-tools; extra == 'dev'
Requires-Dist: pytest; extra == 'dev'
